LICENSE
MANIFEST.in
README.rst
requirements.txt
setup.py
ccuapi/__init__.py
ccuapi/ccu_purge.py
ccuapi/exceptions.py
ccuapi/purge.py
ccuapi/test.py
ccuapi.egg-info/PKG-INFO
ccuapi.egg-info/SOURCES.txt
ccuapi.egg-info/dependency_links.txt
ccuapi.egg-info/entry_points.txt
ccuapi.egg-info/not-zip-safe
ccuapi.egg-info/requires.txt
ccuapi.egg-info/top_level.txt