Metadata-Version: 1.0
Name: ccuapi
Version: 1.2.0
Summary: Python wrapper around Akamai's Content Control Utility API
Home-page: https://github.com/dpetzel/python-ccuapi
Author: David Petzel
Author-email: david.petzel@disney.com
License: BSD 3 Clause License
Platform: UNKNOWN
